spinsim/__init__.py
spinsim-1.0.0.dist-info/LICENSE.rst
spinsim-1.0.0.dist-info/WHEEL
spinsim-1.0.0.dist-info/METADATA
spinsim-1.0.0.dist-info/RECORD
