Metadata-Version: 2.1
Name: spinsim
Version: 1.0.0
Summary: A package for simulating spin half and spin one quantum systems quickly and accurately using cuda parallelisation.
License: BSD-3-Clause
Author: Alexander Tritt
Author-email: alexander.tritt@monash.edu
Requires-Python: >=3.7,<4.0
Classifier: License :: OSI Approved :: BSD License
Classifier: Programming Language :: Python :: 3
Classifier: Programming Language :: Python :: 3.7
Classifier: Programming Language :: Python :: 3.8
Classifier: Programming Language :: Python :: 3.9
Requires-Dist: matplotlib (>=3.2,<3.3)
Requires-Dist: numba (>=0.50.1,<0.51.0)
Requires-Dist: numpy (==1.19.3)
